boto-stubs/METADATA.toml
boto-stubs/__init__.pyi
boto-stubs/auth.pyi
boto-stubs/auth_handler.pyi
boto-stubs/compat.pyi
boto-stubs/connection.pyi
boto-stubs/exception.pyi
boto-stubs/plugin.pyi
boto-stubs/py.typed
boto-stubs/regioninfo.pyi
boto-stubs/utils.pyi
boto-stubs/ec2/__init__.pyi
boto-stubs/elb/__init__.pyi
boto-stubs/kms/__init__.pyi
boto-stubs/kms/exceptions.pyi
boto-stubs/kms/layer1.pyi
boto-stubs/s3/__init__.pyi
boto-stubs/s3/acl.pyi
boto-stubs/s3/bucket.pyi
boto-stubs/s3/bucketlistresultset.pyi
boto-stubs/s3/bucketlogging.pyi
boto-stubs/s3/connection.pyi
boto-stubs/s3/cors.pyi
boto-stubs/s3/deletemarker.pyi
boto-stubs/s3/key.pyi
boto-stubs/s3/keyfile.pyi
boto-stubs/s3/lifecycle.pyi
boto-stubs/s3/multidelete.pyi
boto-stubs/s3/multipart.pyi
boto-stubs/s3/prefix.pyi
boto-stubs/s3/tagging.pyi
boto-stubs/s3/user.pyi
boto-stubs/s3/website.pyi
types_boto-2.49.18.20241019.dist-info/METADATA
types_boto-2.49.18.20241019.dist-info/WHEEL
types_boto-2.49.18.20241019.dist-info/top_level.txt
types_boto-2.49.18.20241019.dist-info/RECORD
